helloworld.py
helloworld_phil_davies-0.0.1.dist-info/METADATA
helloworld_phil_davies-0.0.1.dist-info/WHEEL
helloworld_phil_davies-0.0.1.dist-info/top_level.txt
helloworld_phil_davies-0.0.1.dist-info/RECORD
