Metadata-Version: 2.1
Name: helloworld-phil-davies
Version: 0.0.1
Summary: Say Hello
Home-page: UNKNOWN
Author: Phil Davies
Author-email: phildavies265@gmail.com
License: UNKNOWN
Platform: UNKNOWN
